compas_cadwork/__init__.py
compas_cadwork/storage.py
compas_cadwork/conversions/__init__.py
compas_cadwork/conversions/primitives.py
compas_cadwork/datamodel/__init__.py
compas_cadwork/datamodel/dimension.py
compas_cadwork/datamodel/element.py
compas_cadwork/scene/__init__.py
compas_cadwork/scene/beamobject.py
compas_cadwork/scene/camera.py
compas_cadwork/scene/instructionobject.py
compas_cadwork/scene/scene.py
compas_cadwork/utilities/__init__.py
compas_cadwork/utilities/events.py
compas_cadwork/utilities/ifc_export.py
compas_cadwork-0.10.0.dist-info/licenses/LICENSE
compas_cadwork-0.10.0.dist-info/METADATA
compas_cadwork-0.10.0.dist-info/WHEEL
compas_cadwork-0.10.0.dist-info/top_level.txt
compas_cadwork-0.10.0.dist-info/RECORD
