Metadata-Version: 2.4
Name: compas_cadwork
Version: 0.10.0
Summary: COMPAS package for integrating with cadwork.
Author-email: Chen Kasirer <kasirer@arch.ethz.ch>, Matthias Helmreich <helmreich@arch.ethz.ch>, Gonzalo Casas <casas@arch.ethz.ch>
License: MIT License
Project-URL: Homepage, https://gramaziokohler.github.io/compas_cadwork/latest/
Project-URL: Repository, https://github.com/gramaziokohler/compas_cadwork
Classifier: Development Status :: 4 - Beta
Classifier: Topic :: Scientific/Engineering
Classifier: Programming Language :: Python
Classifier: Programming Language :: Python :: 3
Classifier: Programming Language :: Python :: 3.9
Classifier: Programming Language :: Python :: 3.10
Classifier: Programming Language :: Python :: 3.11
Requires-Python: >=3.9
License-File: LICENSE
Requires-Dist: cwapi3d>=30.498.0
Requires-Dist: compas_timber>=0.11.0
Provides-Extra: dev
Requires-Dist: attrs>=17.4; extra == "dev"
Requires-Dist: black; extra == "dev"
Requires-Dist: bump-my-version; extra == "dev"
Requires-Dist: compas_invocations2; extra == "dev"
Requires-Dist: invoke>=0.14; extra == "dev"
Requires-Dist: sphinx_compas2_theme; extra == "dev"
Requires-Dist: twine; extra == "dev"
Requires-Dist: wheel; extra == "dev"
Requires-Dist: ruff; extra == "dev"
Requires-Dist: build; extra == "dev"
Dynamic: license-file
